dihub/__init__.py
dihub/__internal/__init__.py
dihub/__internal/delegates/__init__.py
dihub/__internal/delegates/injected_delegate.py
dihub/__internal/delegates/module_delegate.py
dihub/__internal/delegates/provider_delegate.py
dihub/__internal/delegates/provider_delegate_test.py
dihub/__internal/helpers/__init__.py
dihub/__internal/helpers/annotation_of.py
dihub/__internal/helpers/class_helper.py
dihub/__internal/helpers/validator.py
dihub/__internal/proxies/__init__.py
dihub/__internal/proxies/primitive_proxy.py
dihub/__internal/proxies/provider_proxy.py
dihub/constants.py
dihub/decorators/__init__.py
dihub/decorators/configurable.py
dihub/decorators/export.py
dihub/decorators/for_root.py
dihub/decorators/inject.py
dihub/decorators/module.py
dihub/decorators/provider.py
dihub/decorators/root.py
dihub/decorators_test.py
dihub/exceptions.py
dihub/plugins/__init__.py
dihub/plugins/asgi.py
dihub/py.typed
dihub/types.py
dihub-0.1.10.dist-info/LICENSE
dihub-0.1.10.dist-info/METADATA
dihub-0.1.10.dist-info/WHEEL
dihub-0.1.10.dist-info/RECORD
